nao/__init__.py
nao/sqlalchemy.py
nao/types.py
nao/ext/__init__.py
nao/ext/flask.py
nao/ext/sqlalchemy.py
nao-0.2.11.dist-info/AUTHORS
nao-0.2.11.dist-info/LICENSE
nao-0.2.11.dist-info/METADATA
nao-0.2.11.dist-info/WHEEL
nao-0.2.11.dist-info/top_level.txt
nao-0.2.11.dist-info/RECORD
